websocket_rs-0.1.0.dist-info/METADATA
websocket_rs-0.1.0.dist-info/WHEEL
websocket_rs-0.1.0.dist-info/licenses/LICENSE
websocket_rs/__init__.py
websocket_rs/websocket_rs.pyd
websocket_rs-0.1.0.dist-info/RECORD
