Metadata-Version: 2.4
Name: websocket-rs
Version: 0.1.0
Classifier: Programming Language :: Rust
Classifier: Programming Language :: Python :: Implementation :: CPython
Classifier: Programming Language :: Python :: Implementation :: PyPy
Classifier: Programming Language :: Python :: 3
Classifier: Programming Language :: Python :: 3.7
Classifier: Programming Language :: Python :: 3.8
Classifier: Programming Language :: Python :: 3.9
Classifier: Programming Language :: Python :: 3.10
Classifier: Programming Language :: Python :: 3.11
Classifier: License :: OSI Approved :: MIT License
Classifier: Development Status :: 4 - Beta
Classifier: Intended Audience :: Developers
Classifier: Topic :: Software Development :: Libraries
Classifier: Topic :: Communications
License-File: LICENSE
Summary: High-performance WebSocket client library for Python using Rust
Keywords: websocket,rust,async,high-performance,client
Author-email: Your Name <your.email@example.com>
License: MIT
Requires-Python: >=3.7
Project-URL: Homepage, https://github.com/yourusername/websocket-rs
Project-URL: Bug Tracker, https://github.com/yourusername/websocket-rs/issues
Project-URL: Documentation, https://github.com/yourusername/websocket-rs#readme
Project-URL: Source Code, https://github.com/yourusername/websocket-rs
